OScofo/__init__.py
OScofo/_OScofo.cp312-win32.pyd
oscofo-0.1.3.post4.dist-info/METADATA
oscofo-0.1.3.post4.dist-info/WHEEL
oscofo-0.1.3.post4.dist-info/licenses/LICENSE
oscofo-0.1.3.post4.dist-info/RECORD
