Metadata-Version: 2.1
Name: OScofo
Version: 0.1.3.post4
Summary: OScofo is an OpenSource Score Follower based on the Research of Cont (2010).
Author-Email: "Charles K. Neimog" <charlesneimog@outlook.com>
Requires-Python: <3.14,>=3.10
